havaj/__init__.py
havaj/mesh_db.py
havaj/mesh_run.py
havaj-0.0.1.dist-info/METADATA
havaj-0.0.1.dist-info/WHEEL
havaj-0.0.1.dist-info/top_level.txt
havaj-0.0.1.dist-info/RECORD
