Metadata-Version: 2.4
Name: havaj
Version: 0.0.1
Summary: This is the simplest module for quick work with files.
Home-page: https://github.com/saiyan05122004
Author: havaj
Author-email: abdyla05122004@gmail.com
Project-URL: GitHub, https://github.com/saiyan05122004
Keywords: files speedfiles
Classifier: Programming Language :: Python :: 3.11
Classifier: License :: OSI Approved :: MIT License
Classifier: Operating System :: OS Independent
Requires-Python: >=3.6
Requires-Dist: requests>=2.25.1
Dynamic: author
Dynamic: author-email
Dynamic: classifier
Dynamic: description
Dynamic: description-content-type
Dynamic: home-page
Dynamic: keywords
Dynamic: project-url
Dynamic: requires-dist
Dynamic: requires-python
Dynamic: summary
